anomed_challenge/__init__.py
anomed_challenge/challenge.py
anomed_challenge/challenge_server.py
anomed_challenge-0.0.21.dist-info/METADATA
anomed_challenge-0.0.21.dist-info/WHEEL
anomed_challenge-0.0.21.dist-info/licenses/LICENSE
anomed_challenge-0.0.21.dist-info/RECORD
