Metadata-Version: 2.4
Name: anomed-challenge
Version: 0.0.21
Summary: A library aiding to create challenges for the AnoMed competition platform.
Project-URL: documentation, https://anomed-challenge.readthedocs.io/en/latest/
Project-URL: source, https://github.com/ypotdevin/anomed_challenge
Author-email: Yannik Potdevin <ypo.uzl@proton.me>
Maintainer-email: Yannik Potdevin <ypo.uzl@proton.me>
License: MIT License
License-File: LICENSE
Classifier: Development Status :: 1 - Planning
Classifier: Intended Audience :: Developers
Requires-Python: >=3.10
Requires-Dist: anomed-utils
Requires-Dist: falcon~=4.0
Requires-Dist: numpy~=1.26
Requires-Dist: pandas~=2.2
Requires-Dist: requests~=2.32
Provides-Extra: dev
Requires-Dist: ruff~=0.7; extra == 'dev'
Provides-Extra: test
Requires-Dist: coverage~=7.6; extra == 'test'
Requires-Dist: pytest-mock~=3.14; extra == 'test'
Requires-Dist: pytest~=8.3; extra == 'test'
Requires-Dist: urllib3~=2.3; extra == 'test'
